gap/pkg/semigroups/CHANGELOG.md
gap/pkg/semigroups/CONTRIBUTING.md
gap/pkg/semigroups/GNUmakefile
gap/pkg/semigroups/GNUmakefile.in
gap/pkg/semigroups/GPL
gap/pkg/semigroups/LICENSE
gap/pkg/semigroups/Makefile
gap/pkg/semigroups/Makefile.gappkg
gap/pkg/semigroups/PackageInfo.g
gap/pkg/semigroups/README.md
gap/pkg/semigroups/VERSIONS
gap/pkg/semigroups/aclocal.m4
gap/pkg/semigroups/autogen.sh
gap/pkg/semigroups/config.guess
gap/pkg/semigroups/config.log
gap/pkg/semigroups/config.status
gap/pkg/semigroups/config.sub
gap/pkg/semigroups/configure
gap/pkg/semigroups/configure.ac
gap/pkg/semigroups/environment.yml
gap/pkg/semigroups/init.g
gap/pkg/semigroups/makedoc.g
gap/pkg/semigroups/prerequisites.sh
gap/pkg/semigroups/read.g
gap/pkg/semigroups/release.toml
gap/pkg/semigroups/bin/aarch64-unknown-linux-musl-default64-kv10/semigroups.so
gap/pkg/semigroups/data/doc/greens.pickle
gap/pkg/semigroups/data/gens/fullbool-8.pickle.gz
gap/pkg/semigroups/data/gens/fullbool.pickle.gz
gap/pkg/semigroups/data/gens/hall.pickle.gz
gap/pkg/semigroups/data/gens/reflex-6.pickle.gz
gap/pkg/semigroups/data/gens/reflex.pickle.gz
gap/pkg/semigroups/data/tst/bipart4
gap/pkg/semigroups/data/tst/pperm10
gap/pkg/semigroups/data/tst/tables.gz
gap/pkg/semigroups/data/tst/testdata
gap/pkg/semigroups/data/tst/testinstall.pickle
gap/pkg/semigroups/data/tst/trans3
gap/pkg/semigroups/data/tst/trans3-old
gap/pkg/semigroups/gap/obsolete.gd
gap/pkg/semigroups/gap/obsolete.gi
gap/pkg/semigroups/gap/options.g
gap/pkg/semigroups/gap/attributes/acting.gd
gap/pkg/semigroups/gap/attributes/acting.gi
gap/pkg/semigroups/gap/attributes/attr.gd
gap/pkg/semigroups/gap/attributes/attr.gi
gap/pkg/semigroups/gap/attributes/dual.gd
gap/pkg/semigroups/gap/attributes/dual.gi
gap/pkg/semigroups/gap/attributes/factor.gd
gap/pkg/semigroups/gap/attributes/factor.gi
gap/pkg/semigroups/gap/attributes/homomorph.gd
gap/pkg/semigroups/gap/attributes/homomorph.gi
passagemath_gap_pkg_semigroups-10.6.43.dist-info/METADATA
passagemath_gap_pkg_semigroups-10.6.43.dist-info/METADATA.bak
passagemath_gap_pkg_semigroups-10.6.43.dist-info/WHEEL
passagemath_gap_pkg_semigroups-10.6.43.dist-info/top_level.txt
passagemath_gap_pkg_semigroups-10.6.43.dist-info/RECORD
